dlc_run/__init__.py
dlc_run/dlc_run.py
dlc_run/version.py
dlc_run-0.0.5.data/data/README.md
dlc_run-0.0.5.dist-info/LICENSE
dlc_run-0.0.5.dist-info/METADATA
dlc_run-0.0.5.dist-info/WHEEL
dlc_run-0.0.5.dist-info/entry_points.txt
dlc_run-0.0.5.dist-info/top_level.txt
dlc_run-0.0.5.dist-info/RECORD
