Metadata-Version: 2.1
Name: dlc-run
Version: 0.0.5
Summary: DLC Run
Home-page: https://github.com/Harold-lkk/dlc_run
License: Apache 2.0
Keywords: dlc
Platform: UNKNOWN
